{
	"name": "SHARE_TEMP_TRAN_COUPON_RECORD",
	"properties": {
		"description": "\n",
		"linkedServiceName": {
			"referenceName": "1crmTagMgmtFileShare",
			"type": "LinkedServiceReference"
		},
		"folder": {
			"name": "SFMC"
		},
		"annotations": [],
		"type": "DelimitedText",
		"typeProperties": {
			"location": {
				"type": "AzureFileStorageLocation",
				"fileName": {
					"value": "@concat('TRAN_COUPON_RECORD_',formatDateTime(convertTimeZone(utcNow(),'UTC','China Standard Time'),'yyyyMMdd'),'.csv.gz')",
					"type": "Expression"
				},
				"folderPath": {
					"value": "@formatDateTime(convertTimeZone(utcNow(),'UTC','China Standard Time'),'yyyyMMdd')",
					"type": "Expression"
				}
			},
			"columnDelimiter": "|",
			"compressionCodec": "gzip",
			"escapeChar": "\\",
			"firstRowAsHeader": true,
			"quoteChar": "\""
		},
		"schema": []
	},
	"type": "Microsoft.DataFactory/factories/datasets"
}